setup.cfg
setup.py
hncapiclient/__init__.py
hncapiclient/backend.py
hncapiclient/cached.py
hncapiclient/test.py
hncapiclient.egg-info/PKG-INFO
hncapiclient.egg-info/SOURCES.txt
hncapiclient.egg-info/dependency_links.txt
hncapiclient.egg-info/entry_points.txt
hncapiclient.egg-info/requires.txt
hncapiclient.egg-info/top_level.txt
hncapiclient.egg-info/zip-safe