Metadata-Version: 1.0
Name: hncapiclient
Version: 0.1.6dev
Summary: json api client for HnC
Home-page: http://www.hackandcraft.com
Author: Martin Peschke
Author-email: martin@hackandcraft.com
License: UNKNOWN
Platform: UNKNOWN
